{
  "next_n": 295147912926237549857,
  "chunk_size": 500000,
  "chunks_issued": 13118866,
  "chunks_done": 13118733,
  "total_tested": 4829690988000,
  "fails": 0,
  "worker_stats": {
    "a37ef45d-c5aa-45b9-a8be-40defebbb9e6": {
      "name": "kf",
      "chunks": 271394,
      "tested": 542788000,
      "fails": 0,
      "total_sec": 1998.3470000003065,
      "first_seen": "2026-03-31 00:31:19",
      "last_seen": "2026-04-04 00:02:02"
    },
    "1bc56ada-8d9d-4c94-bc04-ef358eb54b94": {
      "name": "Collatz-Frontier-Worker1",
      "chunks": 2218063,
      "tested": 1109031500000,
      "fails": 0,
      "total_sec": 2053562.9867830276,
      "first_seen": "2026-03-31 00:31:22",
      "last_seen": "2026-04-24 00:59:59"
    },
    "2b2037b2-852b-424e-b91e-230acaccdf2a": {
      "name": "Collatz-Frontier-Worker0",
      "chunks": 1716604,
      "tested": 858302000000,
      "fails": 0,
      "total_sec": 2057115.821428299,
      "first_seen": "2026-03-31 00:31:22",
      "last_seen": "2026-04-24 00:59:59"
    },
    "DESKTOP-IU5CS8D": {
      "name": "DESKTOP-IU5CS8D",
      "chunks": 829416,
      "tested": 414708000000,
      "fails": 0,
      "total_sec": 118140.37043030358,
      "first_seen": "2026-03-31 00:31:22",
      "last_seen": "2026-04-23 21:00:27"
    },
    "da": {
      "name": "da",
      "chunks": 330926,
      "tested": 661852000,
      "fails": 0,
      "total_sec": 331.9899999990881,
      "first_seen": "2026-03-31 00:31:22",
      "last_seen": "2026-04-02 06:18:28"
    },
    "f65182fc-99da-4cb9-8a57-f7832dcecd46": {
      "name": "Collatz-Frontier-Worker2",
      "chunks": 2053044,
      "tested": 1026522000000,
      "fails": 0,
      "total_sec": 2055161.0209078789,
      "first_seen": "2026-03-31 00:31:22",
      "last_seen": "2026-04-24 00:59:59"
    },
    "60b53a8b-e81e-4722-85de-e53642bf3198": {
      "name": "ITS-SL23-3890-WW",
      "chunks": 1349132,
      "tested": 2698264000,
      "fails": 0,
      "total_sec": 9699.649000176138,
      "first_seen": "2026-03-31 00:31:23",
      "last_seen": "2026-04-08 01:15:41"
    },
    "c5680521-480e-4288-b584-51243d9c7376": {
      "name": "DESKTOP-IU5CS8D-WW",
      "chunks": 385618,
      "tested": 771236000,
      "fails": 0,
      "total_sec": 3316.241000001895,
      "first_seen": "2026-03-31 10:16:50",
      "last_seen": "2026-04-02 20:38:19"
    },
    "0bd2c1bb-ed26-43ac-84a1-2dbbc54333a8": {
      "name": "ITS-SL23-3890",
      "chunks": 2687071,
      "tested": 1343535500000,
      "fails": 0,
      "total_sec": 287008.45538043976,
      "first_seen": "2026-03-31 10:26:54",
      "last_seen": "2026-04-24 00:59:59"
    },
    "9e331a72-8b82-4dfb-857b-c273d2b70ad9": {
      "name": "DESKTOP-IU5CS8D-WW",
      "chunks": 41631,
      "tested": 83262000,
      "fails": 0,
      "total_sec": 235.97499999994457,
      "first_seen": "2026-04-02 20:50:44",
      "last_seen": "2026-04-03 00:38:18"
    },
    "bb7fb2f7-686e-42de-a27f-f7145a67a4c6": {
      "name": "DESKTOP-87NS8M9",
      "chunks": 17612,
      "tested": 8806000000,
      "fails": 0,
      "total_sec": 6884.648370504379,
      "first_seen": "2026-04-02 20:56:07",
      "last_seen": "2026-04-03 13:10:01"
    },
    "c64a8178-4054-4537-bfbb-8b28042695f4": {
      "name": "ITS-SL23-3890-WW",
      "chunks": 1094543,
      "tested": 2189086000,
      "fails": 0,
      "total_sec": 4392.075000011859,
      "first_seen": "2026-04-08 17:03:15",
      "last_seen": "2026-04-15 13:40:32"
    },
    "ac276d4f-178f-44a9-8b34-448b3e7034df": {
      "name": "Collatz-Frontier-Worker3",
      "chunks": 123601,
      "tested": 61800500000,
      "fails": 0,
      "total_sec": 183997.7981760502,
      "first_seen": "2026-04-21 16:40:41",
      "last_seen": "2026-04-24 00:59:59"
    }
  },
  "milestone_log": {
    "Trillion": {
      "value": "1000000000000",
      "crossed_at": "before 2026 (pre-verified by prior work)",
      "worker": "Oliveira e Silva et al. (2010)",
      "frontier_n": "295147905179352825856"
    },
    "Quadrillion": {
      "value": "1000000000000000",
      "crossed_at": "before 2026 (pre-verified by prior work)",
      "worker": "Oliveira e Silva et al. (2010)",
      "frontier_n": "295147905179352825856"
    },
    "Quintillion": {
      "value": "1000000000000000000",
      "crossed_at": "before 2026 (pre-verified by prior work)",
      "worker": "Oliveira e Silva et al. (2010)",
      "frontier_n": "295147905179352825856"
    }
  },
  "worker_registry": {
    "a37ef45d-c5aa-45b9-a8be-40defebbb9e6": {
      "name": "kf",
      "hostname": "web-worker",
      "ip": "173.187.45.56",
      "first_seen": "2026-03-31 00:31:19",
      "last_seen": "2026-04-04 00:02:02"
    },
    "f65182fc-99da-4cb9-8a57-f7832dcecd46": {
      "name": "Collatz-Frontier-Worker2",
      "hostname": "Collatz-Frontier-Worker2",
      "ip": "164.92.83.33",
      "first_seen": "2026-03-31 00:31:21",
      "last_seen": "2026-04-24 00:59:59"
    },
    "1bc56ada-8d9d-4c94-bc04-ef358eb54b94": {
      "name": "Collatz-Frontier-Worker1",
      "hostname": "Collatz-Frontier-Worker1",
      "ip": "64.23.159.163",
      "first_seen": "2026-03-31 00:31:21",
      "last_seen": "2026-04-24 00:59:59"
    },
    "2b2037b2-852b-424e-b91e-230acaccdf2a": {
      "name": "Collatz-Frontier-Worker0",
      "hostname": "Collatz-Frontier-Worker0",
      "ip": "164.92.65.173",
      "first_seen": "2026-03-31 00:31:21",
      "last_seen": "2026-04-24 00:59:59"
    },
    "60b53a8b-e81e-4722-85de-e53642bf3198": {
      "name": "ITS-SL23-3890-WW",
      "hostname": "web-worker",
      "ip": "173.187.45.56",
      "first_seen": "2026-03-31 00:31:23",
      "last_seen": "2026-04-08 01:15:41"
    },
    "c5680521-480e-4288-b584-51243d9c7376": {
      "name": "DESKTOP-IU5CS8D-WW",
      "hostname": "web-worker",
      "ip": "173.187.45.56",
      "first_seen": "2026-03-31 10:16:50",
      "last_seen": "2026-04-02 20:38:19"
    },
    "0bd2c1bb-ed26-43ac-84a1-2dbbc54333a8": {
      "name": "ITS-SL23-3890",
      "hostname": "ITS-SL23-3890",
      "ip": "173.187.45.56",
      "first_seen": "2026-03-31 10:26:54",
      "last_seen": "2026-04-24 00:59:59"
    },
    "9e331a72-8b82-4dfb-857b-c273d2b70ad9": {
      "name": "Browser-h0y5",
      "hostname": "web-worker",
      "ip": "173.187.45.56",
      "first_seen": "2026-04-02 20:50:44",
      "last_seen": "2026-04-03 00:38:18"
    },
    "bb7fb2f7-686e-42de-a27f-f7145a67a4c6": {
      "name": "DESKTOP-87NS8M9",
      "hostname": "DESKTOP-87NS8M9",
      "ip": "173.187.45.56",
      "first_seen": "2026-04-02 20:56:05",
      "last_seen": "2026-04-03 13:10:01"
    },
    "c64a8178-4054-4537-bfbb-8b28042695f4": {
      "name": "ITS-SL23-3890-WW",
      "hostname": "web-worker",
      "ip": "173.187.45.56",
      "first_seen": "2026-04-08 17:03:15",
      "last_seen": "2026-04-15 13:40:32"
    },
    "ac276d4f-178f-44a9-8b34-448b3e7034df": {
      "name": "Collatz-Frontier-Worker3",
      "hostname": "Collatz-Frontier-Worker3",
      "ip": "159.223.171.127",
      "first_seen": "2026-04-21 16:40:38",
      "last_seen": "2026-04-24 00:59:59"
    }
  },
  "_upload_note": "coordinator_secret has been redacted for security. This file cannot be used to verify prize claims without the original secret."
}